Image_dev/AfterCreation.py
Image_dev/Config.txt
Image_dev/ExcuteAmphenol.py
Image_dev/ExcuteThread.py
Image_dev/ExtractImageName.py
Image_dev/Master.py
Image_dev/OracelConnection.py
Image_dev/ReadFile.py
Image_dev/Resize_HashCode_Exclude.py
Image_dev/SendRequests.py
Image_dev/__init__.py
Image_dev/offlineFile.py
Image_dev/instantclient/BASIC_LITE_LICENSE
Image_dev/instantclient/BASIC_LITE_README
Image_dev/instantclient/adrci.exe
Image_dev/instantclient/adrci.sym
Image_dev/instantclient/genezi.exe
Image_dev/instantclient/genezi.sym
Image_dev/instantclient/oci.dll
Image_dev/instantclient/oci.sym
Image_dev/instantclient/ocijdbc21.dll
Image_dev/instantclient/ocijdbc21.sym
Image_dev/instantclient/ociw32.dll
Image_dev/instantclient/ociw32.sym
Image_dev/instantclient/ojdbc8.jar
Image_dev/instantclient/orannzsbb.dll
Image_dev/instantclient/orannzsbb.sym
Image_dev/instantclient/oraocci21.dll
Image_dev/instantclient/oraocci21.sym
Image_dev/instantclient/oraocci21d.dll
Image_dev/instantclient/oraocci21d.sym
Image_dev/instantclient/oraociicus.dll
Image_dev/instantclient/oraociicus.sym
Image_dev/instantclient/orasql.dll
Image_dev/instantclient/orasql.sym
Image_dev/instantclient/ucp.jar
Image_dev/instantclient/uidrvci.exe
Image_dev/instantclient/uidrvci.sym
Image_dev/instantclient/xstreams.jar
Image_dev/instantclient/network/admin/README
Image_dev-1.0.4.dist-info/METADATA
Image_dev-1.0.4.dist-info/WHEEL
Image_dev-1.0.4.dist-info/top_level.txt
Image_dev-1.0.4.dist-info/RECORD
