Metadata-Version: 2.1
Name: Image_dev
Version: 1.0.4
Summary: Image Development project Project
Author: Hamdi Emad
Author-email: hamdy1721998@gmail.com
